netbox_network_canvas_plugin/__init__.py
netbox_network_canvas_plugin/filtersets.py
netbox_network_canvas_plugin/forms.py
netbox_network_canvas_plugin/models.py
netbox_network_canvas_plugin/navigation.py
netbox_network_canvas_plugin/tables.py
netbox_network_canvas_plugin/urls.py
netbox_network_canvas_plugin/views.py
netbox_network_canvas_plugin/api/__init__.py
netbox_network_canvas_plugin/api/serializers.py
netbox_network_canvas_plugin/api/urls.py
netbox_network_canvas_plugin/api/viewsets.py
netbox_network_canvas_plugin/migrations/0001_initial.py
netbox_network_canvas_plugin/migrations/0002_update_model_structure.py
netbox_network_canvas_plugin/migrations/__init__.py
netbox_network_canvas_plugin/static/netbox_network_canvas_plugin/topology.css
netbox_network_canvas_plugin/static/netbox_network_canvas_plugin/js/README.md
netbox_network_canvas_plugin/static/netbox_network_canvas_plugin/js/d3.v7.min.js
netbox_network_canvas_plugin/templates/netbox_network_canvas_plugin/dashboard.html
netbox_network_canvas_plugin/templates/netbox_network_canvas_plugin/dashboard_enhanced.html
netbox_network_canvas_plugin/templates/netbox_network_canvas_plugin/dashboard_enhanced_v0.1.4_style.html
netbox_network_canvas_plugin/templates/netbox_network_canvas_plugin/dashboard_simple.html
netbox_network_canvas_plugin/templates/netbox_network_canvas_plugin/network-canvas-old.html
netbox_network_canvas_plugin/templates/netbox_network_canvas_plugin/network-canvas.html
netbox_network_canvas_plugin/templates/netbox_network_canvas_plugin/networktopologycanvas.html
netbox_network_canvas_plugin/templates/netbox_network_canvas_plugin/networktopologycanvas_delete.html
netbox_network_canvas_plugin/templates/netbox_network_canvas_plugin/networktopologycanvas_edit.html
netbox_network_canvas_plugin/templates/netbox_network_canvas_plugin/networktopologycanvas_form.html
netbox_network_canvas_plugin/templates/netbox_network_canvas_plugin/networktopologycanvas_list.html
netbox_network_canvas_plugin-0.1.5.dist-info/licenses/LICENSE
netbox_network_canvas_plugin-0.1.5.dist-info/METADATA
netbox_network_canvas_plugin-0.1.5.dist-info/WHEEL
netbox_network_canvas_plugin-0.1.5.dist-info/top_level.txt
netbox_network_canvas_plugin-0.1.5.dist-info/RECORD
