Metadata-Version: 2.4
Name: netbox-network-canvas-plugin
Version: 0.1.5
Summary: Interactive network topology visualization for NetBox DCIM/IPAM data with comprehensive Layer 2/Layer 3 mapping, VLAN visualization, and real-time network discovery.
Author-email: Dan Ashton <dashton956@gmail.com>
Project-URL: Documentation, https://github.com/dashton956-alt/netbox-network-canvas-plugin/blob/main/README.md
Project-URL: Source, https://github.com/dashton956-alt/netbox-network-canvas-plugin
Project-URL: Tracker, https://github.com/dashton956-alt/netbox-network-canvas-plugin/issues
Classifier: Development Status :: 3 - Alpha
Classifier: Intended Audience :: Developers
Classifier: Natural Language :: English
Classifier: Programming Language :: Python :: 3 :: Only
Classifier: Programming Language :: Python :: 3.10
Classifier: Programming Language :: Python :: 3.11
Classifier: Programming Language :: Python :: 3.12
Requires-Python: >=3.10.0
License-File: LICENSE
Provides-Extra: test
Requires-Dist: black==24.3.0; extra == "test"
Requires-Dist: check-manifest==0.49; extra == "test"
Requires-Dist: flake8; extra == "test"
Requires-Dist: flake8-pyproject; extra == "test"
Requires-Dist: pre-commit==3.7.0; extra == "test"
Requires-Dist: pytest==8.1.1; extra == "test"
Dynamic: license-file
